iso3_lookup/__init__.py
iso3_lookup/backend.py
iso3_lookup/data.py
iso3_lookup/external.py
iso3_lookup/lookup.py
iso3_lookup/tests.py
iso3_lookup-0.5.0.dist-info/LICENSE
iso3_lookup-0.5.0.dist-info/METADATA
iso3_lookup-0.5.0.dist-info/WHEEL
iso3_lookup-0.5.0.dist-info/entry_points.txt
iso3_lookup-0.5.0.dist-info/top_level.txt
iso3_lookup-0.5.0.dist-info/RECORD
